haros_plugin_cccc/__init__.py
haros_plugin_cccc/plugin.py
haros_plugin_cccc/plugin.yaml
haros_plugin_ccd/__init__.py
haros_plugin_ccd/plugin.py
haros_plugin_ccd/plugin.yaml
haros_plugin_cppcheck/__init__.py
haros_plugin_cppcheck/plugin.py
haros_plugin_cppcheck/plugin.yaml
haros_plugin_cppcheck/rules.xml
haros_plugin_cpplint/__init__.py
haros_plugin_cpplint/plugin.py
haros_plugin_cpplint/plugin.yaml
haros_plugin_lizard/__init__.py
haros_plugin_lizard/plugin.py
haros_plugin_lizard/plugin.yaml
haros_plugin_mi_calculator/__init__.py
haros_plugin_mi_calculator/plugin.py
haros_plugin_mi_calculator/plugin.yaml
haros_plugin_pylint/__init__.py
haros_plugin_pylint/plugin.py
haros_plugin_pylint/plugin.yaml
haros_plugin_radon/__init__.py
haros_plugin_radon/plugin.py
haros_plugin_radon/plugin.yaml
haros_plugins-1.1.5.dist-info/METADATA
haros_plugins-1.1.5.dist-info/WHEEL
haros_plugins-1.1.5.dist-info/top_level.txt
haros_plugins-1.1.5.dist-info/RECORD
