Metadata-Version: 2.1
Name: haros-plugins
Version: 1.1.5
Summary: Plugin repository for HAROS.
Home-page: https://github.com/git-afsantos/haros_plugins
Author: Andre Santos
Author-email: haros.framework@gmail.com
License: MIT
Keywords: static-analysis ros
Platform: UNKNOWN
Requires-Dist: lizard
Requires-Dist: radon
Requires-Dist: pylint
